{
  "parent": "minecraft:recipes/root",
  "rewards": {
    "recipes": [
      "rftoolsbase:dimensionalshard"
    ]
  },
  "criteria": {
    "gold": {
      "trigger": "minecraft:inventory_changed",
      "conditions": {
        "items": [
          {
            "items": [
              "minecraft:gold_ingot"
            ]
          },
          {
            "items": [
              "minecraft:quartz"
            ]
          },
          {
            "items": [
              "minecraft:redstone"
            ]
          },
          {
            "items": [
              "minecraft:prismarine_shard"
            ]
          },
          {
            "items": [
              "minecraft:diamond"
            ]
          },
          {
            "items": [
              "minecraft:emerald"
            ]
          },
          {
            "items": [
              "minecraft:glowstone_dust"
            ]
          },
          {
            "items": [
              "minecraft:iron_ingot"
            ]
          },
          {
            "items": [
              "minecraft:glass"
            ]
          }
        ]
      }
    },
    "has_the_recipe": {
      "trigger": "minecraft:recipe_unlocked",
      "conditions": {
        "recipe": "rftoolsbase:dimensionalshard"
      }
    }
  },
  "requirements": [
    [
      "gold",
      "has_the_recipe"
    ]
  ]
}